{
    "Affenpinscher": [
      {
        "Food": "1/4 to 1/2 cup of high-quality dry food a day, divided into
        two meals. NOTE: How much your adult dog eats depends on his size, age,
        build, metabolism, and activity level. The quality of dog food
        you buy also makes a difference--the better the dog food, the
        further it will go toward nourishing your dog and the less of it
        you'll need to shake into your dog's bowl.
        Read more at http://dogtime.com/dog-breeds/affenpinscher#e2r6BpYBsK3suEd9.99",

        "Exercise": "Like many toy dog breeds, the Affenpinscher can be
        difficult to housetrain. Crate training is recommended.
        Read more at http://dogtime.com/dog-breeds/affenpinscher#e2r6BpYBsK3suEd9.99"
      }
    ],
    "African": [
      {
        "Food": "No info available at the moment",
        "Exercise": "No info available at the moment"
      }
    ],
    "Airedale": [
      {
        "Food": "Recommended daily amount: 1.5 to 2.5 cups of high-quality dry
        food a day, divided into two meals.Keep your Airedale in good shape by
         measuring his food and feeding him twice a day rather than leaving
         food out all the time. If you're unsure whether he's overweight,
         give him the eye test and the hands-on test.
         Read more at http://dogtime.com/dog-breeds/airedale-terrier#J2IPEKirWGf4zsmU.99",

        "Exercise": "Being a high-energy working dog, the Airedale Terrier
        needs daily exercise. In general, the he remains active and full
        of energy throughout his life. He is not suited to apartment life,
        and needs a home with a large, fenced yard.
        Read more at http://dogtime.com/dog-breeds/airedale-terrier#J2IPEKirWGf4zsmU.99"
      }
    ],
    "Akita": [
      {
        "Food": "Recommended daily amount: 3 to 5 cups of high-quality dry food a day.
        Read more at http://dogtime.com/dog-breeds/akita#mUPGPh6L6fJ5QmMx.99",

        "Exercise": "The Akita is aggressive with other dogs and is especially
        prone to same-sex aggression.Training the willful Akita can be
        challenging and requires understanding, experience, and patience.
        It's best to work with a trainer familiar with the breed,
        but be sure to do the training yourself.
        Read more at http://dogtime.com/dog-breeds/akita#vI0YlIoqjgsjOrgC.99"
      }
    ],

    "Appenzeller": [
      {
        "Food": "None available at the moment",
        "Exercise": "Because he's got a strong work ethic and lots of energy,
        this breed isn't suited to an inactive lifestyle. Provide him with
        training and a job or dog sport he can do, or he'll be an unhappy
        camper. Like other breeds that need lots of exercise and stimulation,
        he can grow bored and destructive if he doesn't get it. He excels at
        agility, herding, and obedience trials.
        Read more at http://dogtime.com/dog-breeds/appenzeller-sennenhunde#ktsILHmf5QEDax4R.99"
      }
    ]
}
